python_fastapi_rest_server_codegen/__init__.py
python_fastapi_rest_server_codegen/codegen.py
python_fastapi_rest_server_codegen/openapi-generator-cli.jar
python_fastapi_rest_server_codegen/python-fastapi-rest-server-codegen-tests.jar
python_fastapi_rest_server_codegen/python-fastapi-rest-server-codegen.jar
python_fastapi_rest_server_codegen-1.8.0.dist-info/METADATA
python_fastapi_rest_server_codegen-1.8.0.dist-info/WHEEL
python_fastapi_rest_server_codegen-1.8.0.dist-info/top_level.txt
python_fastapi_rest_server_codegen-1.8.0.dist-info/RECORD
