Metadata-Version: 2.1
Name: python-fastapi-rest-server-codegen
Version: 1.8.0
Summary: Python rest server codegen for Le Comptoir Des Pharmacies
Home-page: https://bitbucket.org/lecomptoirdespharmacies/lcdp-openapi-codegen
Author: Le Comptoir Des Pharmacies
Author-email: g.thrasibule@lecomptoirdespharmacies.fr
License: Apache-2.0
Keywords: openapi,python-fastapi-rest-server-codegen,openapi3
Platform: UNKNOWN
Requires-Dist: Flask (==2.2.5)
Requires-Dist: Werkzeug (==2.2.2)
Requires-Dist: connexion (==3.1.0)
Requires-Dist: pyjwt (==2.8.0)
Requires-Dist: python-dateutil (>=2.6.0)
